clav/__init__.py
clav/hash.py
clav/iter.py
clav/math.py
clav/net.py
clav/random.py
clav/thread.py
clav/time.py
clav/__tests__/__init__.py
clav/__tests__/datasets.py
clav/__tests__/test_data.py
clav/__tests__/test_hash.py
clav/__tests__/test_net.py
clav/data/__init__.py
clav/data/attribute.py
clav/data/util.py
clav/data/format/__init__.py
clav/data/format/base.py
clav/data/format/json.py
clav/data/format/msgpack.py
clav/data/format/myaml.py
clav/data/format/yaml.py
clav/os/__init__.py
clav/os/fs.py
clav/os/run.py
clav/os/service.py
clav/os/usergroup.py
clav/os/packman/__init__.py
clav/os/packman/alpine.py
clav/os/packman/debian.py
clav/os/packman/redhat.py
clav/text/__init__.py
clav/text/regex.py
clav/text/util.py
clav/text/expander/__init__.py
clav/text/expander/base.py
clav/text/expander/fstring.py
clav/text/expander/jinja2.py
clav/text/expander/strformat.py
clav/text/expander/stringtemplate.py
clav-0.0.4.dist-info/LICENSE
clav-0.0.4.dist-info/METADATA
clav-0.0.4.dist-info/WHEEL
clav-0.0.4.dist-info/top_level.txt
clav-0.0.4.dist-info/RECORD
